{
  "external_id": "begonia_taliensis",
  "name": "Taliensis begonia",
  "latin": "Begonia taliensis",
  "sun": "medium",
  "water": "medium",
  "difficulty": "medium",
  "popular": false,
  "recommended_pot_materials": [
    "ceramic",
    "plastic"
  ],
  "recommended_soil_mixes": [
    "peat-free"
  ],
  "water_required": true,
  "water_interval_days": 7,
  "moisture_required": false,
  "moisture_interval_days": null,
  "fertilize_required": true,
  "fertilize_interval_days": 30,
  "repot_required": true,
  "repot_interval_months": 24,
  "image_hero": "begonia_taliensis.jpg",
  "image_thumb": "begonia_taliensis.jpg",
  "traits": [
    {
      "key": "sun",
      "value": {
        "text": {
          "en": "Bright indirect",
          "pl": "Jasne rozproszone",
          "de": "Hell indirekt",
          "fr": "Lumière indirecte",
          "it": "Luce indiretta",
          "es": "Luz indirecta",
          "pt": "Luz indireta",
          "ar": "ضوء غير مباشر",
          "hi": "अप्रत्यक्ष रोशनी",
          "zh": "明亮散射光",
          "ja": "明るい間接光",
          "ko": "밝은 간접광"
        }
      }
    },
    {
      "key": "soil",
      "value": {
        "text": {
          "en": "Well-drained mix",
          "pl": "Przepuszczalne",
          "de": "Gut drainiert",
          "fr": "Bien drainé",
          "it": "Ben drenato",
          "es": "Bien drenado",
          "pt": "Bem drenado",
          "ar": "تربة جيدة الصرف",
          "hi": "अच्छी जलनिकासी",
          "zh": "排水良好",
          "ja": "水はけ良好",
          "ko": "배수 잘됨"
        }
      }
    },
    {
      "key": "watering",
      "value": {
        "text": {
          "en": "Even moisture",
          "pl": "Równa wilgoć",
          "de": "Gleichmäßig feucht",
          "fr": "Humidité régulière",
          "it": "Umido uniforme",
          "es": "Humedad regular",
          "pt": "Umidade regular",
          "ar": "رطوبة متوازنة",
          "hi": "समान नमी",
          "zh": "保持湿润",
          "ja": "均一な湿り気",
          "ko": "고른 수분"
        }
      }
    },
    {
      "key": "difficulty",
      "value": {
        "text": {
          "en": "Moderate care",
          "pl": "Umiarkowana",
          "de": "Mittel",
          "fr": "Moyenne",
          "it": "Media",
          "es": "Media",
          "pt": "Média",
          "ar": "عناية متوسطة",
          "hi": "मध्यम",
          "zh": "中等",
          "ja": "普通",
          "ko": "보통"
        }
      }
    },
    {
      "key": "temperature",
      "value": {
        "text": {
          "en": "15–24°C",
          "pl": "15–24°C",
          "de": "15–24°C",
          "fr": "15–24°C",
          "it": "15–24°C",
          "es": "15–24°C",
          "pt": "15–24°C",
          "ar": "15–24°م",
          "hi": "15–24°C",
          "zh": "15–24°C",
          "ja": "15–24°C",
          "ko": "15–24°C"
        }
      }
    },
    {
      "key": "humidity",
      "value": {
        "text": {
          "en": "Likes humidity",
          "pl": "Lubi wilgoć",
          "de": "Mag Feuchte",
          "fr": "Aime l’humidité",
          "it": "Ama umidità",
          "es": "Gusta humedad",
          "pt": "Gosta de umidade",
          "ar": "يحب الرطوبة",
          "hi": "नमी पसंद",
          "zh": "喜湿度",
          "ja": "湿度好む",
          "ko": "습도 선호"
        }
      }
    },
    {
      "key": "toxic",
      "value": {
        "text": {
          "en": "Toxic to pets",
          "pl": "Toksyczna",
          "de": "Giftig für Tiere",
          "fr": "Toxique animaux",
          "it": "Tossica animali",
          "es": "Tóxica mascotas",
          "pt": "Tóxica pets",
          "ar": "سامة للحيوانات",
          "hi": "पालतू हेतु विषाक्त",
          "zh": "对宠物有毒",
          "ja": "ペット有毒",
          "ko": "반려동물 유독"
        }
      }
    },
    {
      "key": "growth",
      "value": {
        "text": {
          "en": "Rhizomatous",
          "pl": "Kłączowa",
          "de": "Rhizombildend",
          "fr": "Rhizomateuse",
          "it": "Rizomatosa",
          "es": "Rizomatosa",
          "pt": "Rizomatosa",
          "ar": "جذمور",
          "hi": "राइजोमयुक्त",
          "zh": "根茎型",
          "ja": "根茎性",
          "ko": "근경형"
        }
      }
    },
    {
      "key": "problems",
      "value": {
        "text": {
          "en": "Avoid wet soil",
          "pl": "Nie przelać",
          "de": "Staunässe meiden",
          "fr": "Éviter excès eau",
          "it": "Evita ristagni",
          "es": "Evitar encharque",
          "pt": "Evitar encharcar",
          "ar": "تجنب الغمر",
          "hi": "अधिक पानी न दें",
          "zh": "避免积水",
          "ja": "過湿を避ける",
          "ko": "과습 피하기"
        }
      }
    },
    {
      "key": "pests",
      "value": {
        "text": {
          "en": "Occasional pests",
          "pl": "Sporadyczne",
          "de": "Gelegentlich",
          "fr": "Rares ravageurs",
          "it": "Parassiti rari",
          "es": "Plagas ocasionales",
          "pt": "Pragas ocasionais",
          "ar": "آفات أحيانًا",
          "hi": "कभी-कभी कीट",
          "zh": "偶有害虫",
          "ja": "害虫まれ",
          "ko": "가끔 해충"
        }
      }
    }
  ],
  "translations": {
    "en": {
      "common_name": "Taliensis begonia",
      "description": "Begonia taliensis, commonly called Taliensis begonia, is a begonia plant grown for its foliage. Place it in bright, indirect or filtered light. Use a well-drained potting mix and water when the top layer of the potting mix begins to dry. It prefers higher humidity and temperatures around 15–24°C. Avoid wet soil; keep it away from pets that chew plants."
    },
    "pl": {
      "common_name": "Begonia taliensis",
      "description": "Begonia taliensis to roślina typu begonia, uprawiana ze względu na dekoracyjne liście. Ustaw ją w jasnym, rozproszonym lub filtrowanym świetle. Zastosuj dobrze przepuszczalne podłoże i podlewaj, gdy wierzchnia warstwa podłoża zaczyna przesychać. Preferuje wyższą wilgotność powietrza i temperatury około 15–24°C. Unikaj mokrego, ciężkiego podłoża; trzymaj z dala od zwierząt, które podgryzają rośliny."
    },
    "de": {
      "common_name": "Tali-Begonie",
      "description": "Begonia taliensis, auch Tali-Begonie genannt, ist eine Pflanze vom Typ Begonie und wird vor allem für das Laub kultiviert. Stelle sie an einen Platz mit hellem, indirektem oder gefiltertem Licht. Verwende ein gut drainierendes Substrat und gieße, wenn die obere Substratschicht zu trocknen beginnt. Sie bevorzugt höhere Luftfeuchtigkeit und Temperaturen um 15–24°C. Vermeide nasses, schweres Substrat; von Haustieren fernhalten, die Pflanzen anknabbern."
    },
    "fr": {
      "common_name": "Bégonia taliensis",
      "description": "Begonia taliensis, appelée Bégonia taliensis, est une plante de type bégonia, cultivée pour son feuillage. Placez-la dans une lumière vive indirecte ou filtrée. Utilisez un substrat bien drainant et arrosez quand la surface du substrat commence à sécher. Elle préfère une humidité plus élevée et des températures autour de 15–24°C. Évitez un substrat détrempé et lourd; gardez-la hors de portée des animaux qui mâchonnent les plantes."
    },
    "it": {
      "common_name": "Begonia taliensis",
      "description": "Begonia taliensis è una pianta di tipo begonia, coltivata per il fogliame. Tienila in luce intensa indiretta o filtrata. Usa un substrato ben drenante e annaffia quando lo strato superiore del substrato inizia ad asciugarsi. Preferisce umidità più alta e temperature intorno a 15–24°C. Evita substrato fradicio e pesante; tienila lontana dagli animali che mordicchiano le piante."
    },
    "es": {
      "common_name": "Begonia taliensis",
      "description": "Begonia taliensis es una planta de tipo begonia, cultivada principalmente por su follaje. Colócala con luz brillante indirecta o filtrada. Usa un sustrato con buen drenaje y riega cuando la capa superior del sustrato empiece a secarse. Prefiere humedad más alta y temperaturas alrededor de 15–24°C. Evita un sustrato encharcado y pesado; mantenla lejos de mascotas que muerden plantas."
    },
    "pt": {
      "common_name": "Begônia taliensis",
      "description": "Begonia taliensis, conhecida como Begônia taliensis, é uma planta do tipo begônia, cultivada principalmente para a folhagem. Coloque-a em luz forte indireta ou filtrada. Use um substrato bem drenante e regue quando a camada superior do substrato começar a secar. Prefere umidade mais alta e temperaturas em torno de 15–24°C. Evite substrato encharcado e pesado; mantenha longe de animais que mordiscam plantas."
    },
    "ar": {
      "common_name": "بيغونيا تالينسيس",
      "description": "Begonia taliensis، المعروفة باسم بيغونيا تالينسيس، هي بيجونيا تُزرع من أجل أوراقه الزخرفية. ضعها في ضوء ساطع غير مباشر أو مرشح. استخدم تربة جيدة التصريف واسقِ عندما تبدأ الطبقة العلوية من التربة بالجفاف. تفضل رطوبة أعلى ودرجات حرارة حول 15–24°C. تجنب التربة الثقيلة والمشبعة بالماء; أبعدها عن الحيوانات الأليفة التي تمضغ النباتات."
    },
    "hi": {
      "common_name": "बेगोनिया टालिएन्सिस",
      "description": "Begonia taliensis, जिसे बेगोनिया टालिएन्सिस कहा जाता है, बेगोनिया है जिसे सजावटी पत्तियों के लिए उगाया जाता है। इसे तेज़, अप्रत्यक्ष या छनकर आने वाली रोशनी में रखें। अच्छी जलनिकासी वाला मिश्रण का उपयोग करें और ऊपरी परत सूखने लगे तो पानी दें। इसे अधिक आर्द्रता और लगभग 15–24°C तापमान पसंद है। गीली और भारी मिट्टी से बचें; इसे पौधे चबाने वाले पालतू जानवरों से दूर रखें।"
    },
    "zh": {
      "common_name": "大理秋海棠",
      "description": "Begonia taliensis，通常称为大理秋海棠，是一种秋海棠，主要用于观赏叶片。 放在明亮散射光或过滤光处。 使用排水良好的基质，并表层基质开始变干时再浇水。 它偏好较高空气湿度，温度约15–24°C。 避免基质长期潮湿或过重; 请远离会啃咬植物的宠物。"
    },
    "ja": {
      "common_name": "タリエンシス・ベゴニア",
      "description": "Begonia taliensis（タリエンシス・ベゴニア）は、葉姿を楽しむために育てるベゴニアです。 明るい間接光またはフィルター越しの光に置きます。 水はけの良い用土を使い、用土の表面が乾き始めたら水やりします。 高めの湿度と15–24°C前後の温度を好みます。 湿り過ぎた重い用土を避けます; 植物をかじるペットから離してください。"
    },
    "ko": {
      "common_name": "탈리엔시스 베고니아",
      "description": "Begonia taliensis(탈리엔시스 베고니아)는 잎을/를 위해 기르는 베고니아입니다. 밝은 간접광 또는 여과광에 두세요. 배수가 좋은 흙을 사용하고 겉흙이 마르기 시작하면 물을 주세요. 높은 습도와 약 15–24°C의 온도를 선호합니다. 젖어 있는 무거운 흙을 피하세요; 식물을 씹는 반려동물에게서 멀리 두세요."
    }
  },
  "sources": {
    "urls": [
      "https://www.rhs.org.uk/plants/begonia",
      "https://www.missouribotanicalgarden.org/plantfinder/plantfindersearch.aspx?genus=Begonia",
      "https://powo.science.kew.org/taxon/urn:lsid:ipni.org:names:60431874-2"
    ]
  }
}
