{
  "external_id": "coelogyne_cristata",
  "name": "Crested coelogyne",
  "latin": "Coelogyne cristata",
  "sun": "medium",
  "water": "medium",
  "difficulty": "hard",
  "popular": false,
  "recommended_pot_materials": [
    "plastic"
  ],
  "recommended_soil_mixes": [
    "orchid"
  ],
  "water_required": true,
  "water_interval_days": 7,
  "moisture_required": true,
  "moisture_interval_days": 3,
  "fertilize_required": true,
  "fertilize_interval_days": 14,
  "repot_required": true,
  "repot_interval_months": 24,
  "image_hero": "coelogyne_cristata.jpg",
  "image_thumb": "coelogyne_cristata.jpg",
  "traits": [
    {
      "key": "sun",
      "value": {
        "text": {
          "en": "Bright, indirect",
          "pl": "Jasne, rozproszone",
          "de": "Hell, indirekt",
          "fr": "Lumineux indirect",
          "it": "Luce intensa indiretta",
          "es": "Luz brillante indirecta",
          "pt": "Luz forte indireta",
          "ar": "ضوء ساطع غير مباشر",
          "hi": "तेज़, अप्रत्यक्ष",
          "zh": "明亮散射光",
          "ja": "明るい間接光",
          "ko": "밝은 간접광"
        }
      }
    },
    {
      "key": "soil",
      "value": {
        "text": {
          "en": "Orchid bark mix",
          "pl": "Kora do storczyków",
          "de": "Orchideenrinde",
          "fr": "Écorce d’orchidée",
          "it": "Corteccia per orchidee",
          "es": "Corteza para orquídeas",
          "pt": "Casca para orquídeas",
          "ar": "خليط لحاء للأوركيد",
          "hi": "ऑर्किड बार्क मिक्स",
          "zh": "兰花树皮基质",
          "ja": "バーク培地",
          "ko": "난초 바크 배지"
        }
      }
    },
    {
      "key": "watering",
      "value": {
        "text": {
          "en": "Keep lightly moist",
          "pl": "Lekko wilgotne",
          "de": "Leicht feucht",
          "fr": "Légèrement humide",
          "it": "Leggermente umido",
          "es": "Ligeramente húmedo",
          "pt": "Levemente úmido",
          "ar": "رطوبة خفيفة",
          "hi": "हल्का नम",
          "zh": "保持微湿",
          "ja": "軽く湿らせる",
          "ko": "약간 촉촉하게"
        }
      }
    },
    {
      "key": "difficulty",
      "value": {
        "text": {
          "en": "Needs cool winter rest",
          "pl": "Wymaga chłodnej zimy",
          "de": "Braucht kühlen Winter",
          "fr": "Repos d’hiver frais",
          "it": "Riposo invernale fresco",
          "es": "Reposo invernal fresco",
          "pt": "Repouso frio no inverno",
          "ar": "يحتاج شتاءً بارداً",
          "hi": "ठंडी सर्दी चाहिए",
          "zh": "需凉爽冬季",
          "ja": "涼しい冬の休眠",
          "ko": "서늘한 겨울 휴면"
        }
      }
    },
    {
      "key": "temperature",
      "value": {
        "text": {
          "en": "Cool 10–24°C",
          "pl": "Chłodno 10–24°C",
          "de": "Kühl 10–24°C",
          "fr": "Frais 10–24°C",
          "it": "Fresco 10–24°C",
          "es": "Fresco 10–24°C",
          "pt": "Fresco 10–24°C",
          "ar": "بارد 10–24°م",
          "hi": "ठंडा 10–24°C",
          "zh": "凉爽 10–24°C",
          "ja": "涼しい 10–24°C",
          "ko": "서늘 10–24°C"
        }
      }
    },
    {
      "key": "humidity",
      "value": {
        "text": {
          "en": "Higher humidity",
          "pl": "Wyższa wilgotność",
          "de": "Höhere Luftfeuchte",
          "fr": "Humidité élevée",
          "it": "Umidità alta",
          "es": "Humedad alta",
          "pt": "Umidade alta",
          "ar": "رطوبة أعلى",
          "hi": "अधिक नमी",
          "zh": "较高湿度",
          "ja": "高めの湿度",
          "ko": "높은 습도"
        }
      }
    },
    {
      "key": "toxic",
      "value": {
        "text": {
          "en": "Generally non-toxic",
          "pl": "Zwykle nietoksyczna",
          "de": "Meist ungiftig",
          "fr": "Généralement non toxique",
          "it": "Generalmente non tossica",
          "es": "Generalmente no tóxica",
          "pt": "Geralmente não tóxica",
          "ar": "غير سامة غالباً",
          "hi": "आमतौर पर गैर-विषैली",
          "zh": "通常无毒",
          "ja": "一般に無毒",
          "ko": "대체로 무독성"
        }
      }
    },
    {
      "key": "growth",
      "value": {
        "text": {
          "en": "Clumping pseudobulbs",
          "pl": "Kępy pseudobulw",
          "de": "Horstbildend",
          "fr": "Touffes à pseudobulbes",
          "it": "Ciuffi di pseudobulbi",
          "es": "Macollas de pseudobulbos",
          "pt": "Touceiras de pseudobulbos",
          "ar": "كتل ببصيلات كاذبة",
          "hi": "गुच्छेदार स्यूडोबल्ब",
          "zh": "丛生假鳞茎",
          "ja": "株立ちの偽球茎",
          "ko": "군생 가짜구근"
        }
      }
    },
    {
      "key": "problems",
      "value": {
        "text": {
          "en": "Avoid heat, soggy mix",
          "pl": "Unikaj upału i zalania",
          "de": "Hitze, Staunässe meiden",
          "fr": "Éviter chaleur et détrempe",
          "it": "Evita caldo e ristagni",
          "es": "Evita calor y encharque",
          "pt": "Evite calor e encharque",
          "ar": "تجنب الحرّ والتشبع",
          "hi": "गर्मी व भीगापन नहीं",
          "zh": "避高温与积水",
          "ja": "高温と過湿を避ける",
          "ko": "고온·과습 피하기"
        }
      }
    },
    {
      "key": "pests",
      "value": {
        "text": {
          "en": "Occasional pests",
          "pl": "Sporadyczne szkodniki",
          "de": "Gelegentliche Schädlinge",
          "fr": "Ravageurs occasionnels",
          "it": "Parassiti occasionali",
          "es": "Plagas ocasionales",
          "pt": "Pragas ocasionais",
          "ar": "آفات أحياناً",
          "hi": "कभी-कभी कीट",
          "zh": "偶见虫害",
          "ja": "害虫は時々",
          "ko": "가끔 해충"
        }
      }
    }
  ],
  "translations": {
    "en": {
      "common_name": "Crested coelogyne",
      "description": "A cool-growing Himalayan orchid with fragrant white winter-to-spring flowers and pseudobulbs. Give bright, indirect light and keep the orchid mix lightly moist during active growth, then reduce watering in winter. Cooler winter conditions help trigger blooming."
    },
    "pl": {
      "common_name": "koelogyne grzebieniasta",
      "description": "Chłodolubny storczyk z Himalajów o pachnących białych kwiatach zimą i wiosną oraz pseudobulwach. Zapewnij jasne, rozproszone światło i utrzymuj lekko wilgotne podłoże dla storczyków w okresie wzrostu, a zimą ogranicz podlewanie. Chłodniejsza zima sprzyja zawiązywaniu pąków."
    },
    "de": {
      "common_name": "Kamm-Coelogyne",
      "description": "Eine kühl wachsende Himalaya-Orchidee mit duftenden weißen Blüten im Winter bis Frühling und Pseudobulben. Helles, indirektes Licht geben und das Orchideensubstrat in der Wachstumszeit leicht feucht halten, im Winter sparsamer gießen. Eine kühle Winterphase unterstützt die Blütenbildung."
    },
    "fr": {
      "common_name": "coelogyne crêtée",
      "description": "Orchidée de climat frais originaire de l’Himalaya, à fleurs blanches parfumées de l’hiver au printemps et à pseudobulbes. Offrez une lumière vive indirecte et gardez le substrat à orchidées légèrement humide en période de croissance, puis réduisez l’arrosage en hiver. Un hiver plus frais favorise la floraison."
    },
    "it": {
      "common_name": "coelogyne crestata",
      "description": "Orchidea di montagna dell’Himalaya, amante del fresco, con fiori bianchi profumati tra inverno e primavera e pseudobulbi. Fornisci luce intensa indiretta e mantieni il substrato per orchidee leggermente umido durante la crescita, riducendo l’acqua in inverno. Un inverno più fresco aiuta a stimolare la fioritura."
    },
    "es": {
      "common_name": "coelogyne crestada",
      "description": "Orquídea himalaya de clima fresco con flores blancas fragantes de invierno a primavera y pseudobulbos. Dale luz brillante indirecta y mantén el sustrato de orquídeas ligeramente húmedo durante el crecimiento, reduciendo el riego en invierno. Un invierno más fresco ayuda a inducir la floración."
    },
    "pt": {
      "common_name": "coelogyne crestada",
      "description": "Orquídea do Himalaia de clima fresco, com flores brancas perfumadas do inverno à primavera e pseudobulbos. Forneça luz forte indireta e mantenha o substrato para orquídeas levemente úmido durante o crescimento, reduzindo a rega no inverno. Um inverno mais fresco ajuda a induzir a floração."
    },
    "ar": {
      "common_name": "سيولوجيني كريستاتا",
      "description": "أوركيد جبلي من الهملايا يفضل البرودة وله أزهار بيضاء عطرة من الشتاء إلى الربيع وبصيلات كاذبة. وفر ضوءاً ساطعاً غير مباشر وحافظ على وسط الأوركيد رطباً قليلاً أثناء النمو ثم خفف الري في الشتاء. البرودة الشتوية تساعد على تحفيز الإزهار."
    },
    "hi": {
      "common_name": "कोएलोजाइन क्रिस्टाटा",
      "description": "यह हिमालय की ठंडे मौसम में बढ़ने वाली ऑर्किड है, जिसमें सर्दियों से वसंत तक सुगंधित सफेद फूल और स्यूडोबल्ब होते हैं। तेज़ अप्रत्यक्ष रोशनी दें और बढ़वार के समय ऑर्किड मिक्स को हल्का नम रखें, फिर सर्दियों में पानी कम करें। ठंडी सर्दी फूल आने में मदद करती है।"
    },
    "zh": {
      "common_name": "冠唇贝母兰",
      "description": "源自喜马拉雅的凉爽型兰花，具假鳞茎，冬末至春季开芳香白花。提供明亮散射光，生长季让兰花基质保持微湿，冬季减少浇水。较凉的冬季环境有助于促花。"
    },
    "ja": {
      "common_name": "セロジネ・クリスタータ",
      "description": "ヒマラヤ原産の冷涼性ランで、偽球茎を持ち、冬から春に香りのある白花を咲かせます。明るい間接光で、生育期はバーク培地を軽く湿らせ、冬は水やりを控えます。涼しい冬が開花の助けになります。"
    },
    "ko": {
      "common_name": "코엘로지네 크리스타타",
      "description": "히말라야 원산의 서늘한 환경을 좋아하는 난초로, 가짜구근이 있고 겨울~봄에 향기로운 흰 꽃이 핍니다. 밝은 간접광을 주고 생장기에는 배지를 약간 촉촉하게 유지하되 겨울에는 물주기를 줄이세요. 서늘한 겨울 환경이 개화에 도움이 됩니다."
    }
  },
  "sources": {
    "urls": [
      "https://www.aos.org/orchid-care/orchid-care-and-culture-sheets/coelogyne-culture-sheet/coelogyne-culture",
      "https://www.osgb.org.uk/orchid-care-guides/coelogyne-orchid-care",
      "https://www.rhs.org.uk/plants/4112/coelogyne-cristata/details",
      "https://powo.science.kew.org/taxon/urn:lsid:ipni.org:names:623828-1",
      "https://www.guide-to-houseplants.com/coelogyne-cristata.html",
      "https://www.aspca.org/pet-care/aspca-poison-control/toxic-and-non-toxic-plants/phalaenopsis-orchid"
    ]
  }
}
