{
  "external_id": "dyckia_fosteriana",
  "name": "Foster's dyckia",
  "latin": "Dyckia fosteriana",
  "sun": "high",
  "water": "low",
  "difficulty": "easy",
  "popular": false,
  "recommended_pot_materials": [
    "terracotta"
  ],
  "recommended_soil_mixes": [
    "cactus-succulent"
  ],
  "water_required": true,
  "water_interval_days": 14,
  "moisture_required": false,
  "moisture_interval_days": null,
  "fertilize_required": true,
  "fertilize_interval_days": 30,
  "repot_required": true,
  "repot_interval_months": 30,
  "image_hero": "dyckia_fosteriana.jpg",
  "image_thumb": "dyckia_fosteriana.jpg",
  "traits": [
    {
      "key": "sun",
      "value": {
        "text": {
          "en": "Bright sun",
          "pl": "Jasne słońce",
          "de": "Viel Sonne",
          "fr": "Soleil vif",
          "it": "Sole pieno",
          "es": "Sol brillante",
          "pt": "Sol forte",
          "ar": "شمس ساطعة",
          "hi": "तेज़ धूप",
          "zh": "充足日照",
          "ja": "明るい日光",
          "ko": "밝은 햇빛"
        }
      }
    },
    {
      "key": "soil",
      "value": {
        "text": {
          "en": "Cactus mix",
          "pl": "Podłoże do kakt.",
          "de": "Kakteenerde",
          "fr": "Substrat cactus",
          "it": "Terriccio cactus",
          "es": "Sustrato cactus",
          "pt": "Substrato cactus",
          "ar": "تربة صبارات",
          "hi": "कैक्टस मिट्टी",
          "zh": "多肉土",
          "ja": "多肉用土",
          "ko": "다육용 흙"
        }
      }
    },
    {
      "key": "watering",
      "value": {
        "text": {
          "en": "Dry between water",
          "pl": "Podlewaj po suszy",
          "de": "Zwischen Gaben trock",
          "fr": "Laisser sécher",
          "it": "Asciuga tra annaffi",
          "es": "Dejar secar",
          "pt": "Deixe secar",
          "ar": "اتركها تجف",
          "hi": "सूखने पर पानी",
          "zh": "干透再浇",
          "ja": "乾いてから水",
          "ko": "마른 뒤 물"
        }
      }
    },
    {
      "key": "difficulty",
      "value": {
        "text": {
          "en": "Easy",
          "pl": "Łatwa",
          "de": "Einfach",
          "fr": "Facile",
          "it": "Facile",
          "es": "Fácil",
          "pt": "Fácil",
          "ar": "سهل",
          "hi": "आसान",
          "zh": "容易",
          "ja": "簡単",
          "ko": "쉬움"
        }
      }
    },
    {
      "key": "temperature",
      "value": {
        "text": {
          "en": "10–30°C",
          "pl": "10–30°C",
          "de": "10–30°C",
          "fr": "10–30°C",
          "it": "10–30°C",
          "es": "10–30°C",
          "pt": "10–30°C",
          "ar": "10–30°م",
          "hi": "10–30°C",
          "zh": "10–30°C",
          "ja": "10–30°C",
          "ko": "10–30°C"
        }
      }
    },
    {
      "key": "humidity",
      "value": {
        "text": {
          "en": "Normal indoor",
          "pl": "Zwykła w domu",
          "de": "Normale Raumluft",
          "fr": "Air normal",
          "it": "Umidità normale",
          "es": "Humedad normal",
          "pt": "Umidade normal",
          "ar": "رطوبة عادية",
          "hi": "सामान्य नमी",
          "zh": "普通室内湿度",
          "ja": "普通の湿度",
          "ko": "일반 실내습도"
        }
      }
    },
    {
      "key": "toxic",
      "value": {
        "text": {
          "en": "Not known toxic",
          "pl": "Brak danych o toks.",
          "de": "Nicht bekannt tox.",
          "fr": "Toxicité inconnue",
          "it": "Tossicità ignota",
          "es": "Toxicidad incierta",
          "pt": "Toxicidade incerta",
          "ar": "غير معروف السمية",
          "hi": "विषाक्तता अज्ञात",
          "zh": "毒性不明确",
          "ja": "毒性は不明",
          "ko": "독성 정보 없음"
        }
      }
    },
    {
      "key": "growth",
      "value": {
        "text": {
          "en": "Slow clumping",
          "pl": "Wolno kępi się",
          "de": "Langsam horstend",
          "fr": "Lente en touffe",
          "it": "Crescita lenta",
          "es": "Crecimiento lento",
          "pt": "Crescimento lento",
          "ar": "نمو بطيء",
          "hi": "धीमी बढ़त",
          "zh": "缓慢丛生",
          "ja": "ゆっくり群生",
          "ko": "느리게 군생"
        }
      }
    },
    {
      "key": "problems",
      "value": {
        "text": {
          "en": "Avoid soggy soil",
          "pl": "Unikaj przelania",
          "de": "Keine Staunässe",
          "fr": "Éviter l’excès d’eau",
          "it": "No ristagni",
          "es": "Evita encharcar",
          "pt": "Evite encharcar",
          "ar": "تجنب التربة المبللة",
          "hi": "अधिक पानी न दें",
          "zh": "避免积水",
          "ja": "過湿に注意",
          "ko": "과습 주의"
        }
      }
    },
    {
      "key": "pests",
      "value": {
        "text": {
          "en": "Occasional pests",
          "pl": "Sporadyczne szkodn.",
          "de": "Gelegentl. Schädlinge",
          "fr": "Ravageurs occasionn.",
          "it": "Parassiti occasionali",
          "es": "Plagas ocasionales",
          "pt": "Pragas ocasionais",
          "ar": "آفات أحيانًا",
          "hi": "कभी-कभी कीट",
          "zh": "偶见虫害",
          "ja": "害虫は時々",
          "ko": "가끔 해충"
        }
      }
    }
  ],
  "translations": {
    "en": {
      "common_name": "Foster's dyckia",
      "description": "Dyckia fosteriana is a terrestrial bromeliad from Brazil that forms a stiff, spiny rosette. Give it very bright light to sun and a fast-draining cactus/succulent mix. Water only after the mix dries well; keep it above about 10°C and feed lightly during active growth."
    },
    "pl": {
      "common_name": "dyckia Fostera",
      "description": "Dyckia fosteriana to naziemna bromelia z Brazylii, tworząca sztywną, kolczastą rozetę. Wymaga bardzo jasnego stanowiska i przepuszczalnego podłoża do kaktusów/sukulentów. Podlewaj dopiero po dobrym przeschnięciu i utrzymuj temperaturę powyżej ok. 10°C; w sezonie zasilaj lekko."
    },
    "de": {
      "common_name": "Fosters Dyckie",
      "description": "Dyckia fosteriana ist eine terrestrische Bromelie aus Brasilien mit steifer, stacheliger Rosette. Sie braucht sehr helles Licht bis Sonne und ein stark durchlässiges Kakteen-/Sukkulentensubstrat. Gieße erst nach dem Abtrocknen und halte sie über etwa 10°C; während des Wachstums sparsam düngen."
    },
    "fr": {
      "common_name": "dyckia de Foster",
      "description": "Dyckia fosteriana est une broméliacée terrestre du Brésil formant une rosette rigide et épineuse. Donnez une lumière très vive à du soleil et un substrat très drainant type cactus/succulentes. Arrosez après séchage du mélange, gardez au-dessus d’environ 10°C et fertilisez légèrement en période de croissance."
    },
    "it": {
      "common_name": "dyckia di Foster",
      "description": "Dyckia fosteriana è una bromeliacea terrestre del Brasile con rosetta rigida e spinosa. Richiede luce molto intensa fino a sole e un terriccio molto drenante per cactus/succulente. Annaffia solo quando il substrato è ben asciutto, mantieni sopra circa 10°C e concima leggermente nella fase di crescita."
    },
    "es": {
      "common_name": "dyckia de Foster",
      "description": "Dyckia fosteriana es una bromelia terrestre de Brasil que forma una roseta rígida y espinosa. Necesita luz muy brillante a sol y un sustrato muy drenante para cactus/suculentas. Riega cuando el sustrato se seque bien, mantenla por encima de unos 10°C y abona suave en crecimiento."
    },
    "pt": {
      "common_name": "dyckia de Foster",
      "description": "Dyckia fosteriana é uma bromélia terrestre do Brasil que forma uma roseta rígida e espinhosa. Prefere luz muito forte a sol e um substrato bem drenante para cactos/suculentas. Regue apenas após secar bem, mantenha acima de cerca de 10°C e adube levemente no período de crescimento."
    },
    "ar": {
      "common_name": "ديكيا فوستريانا",
      "description": "Dyckia fosteriana بروميليا أرضية من البرازيل تُكوّن وردة صلبة شائكة. تحتاج إلى ضوء قوي جدًا إلى شمس وتربة سريعة التصريف مثل تربة الصبّارات. اسقِ بعد جفاف التربة جيدًا، وأبقِها فوق نحو 10°م مع تسميد خفيف أثناء النمو."
    },
    "hi": {
      "common_name": "फोस्टर डिकिया",
      "description": "Dyckia fosteriana ब्राज़ील की स्थलीय ब्रोमेलियाड है जो कठोर, काँटेदार रोसेट बनाती है। इसे बहुत तेज़ रोशनी/धूप और अच्छी जलनिकासी वाली कैक्टस/सक्युलेंट मिट्टी दें। मिट्टी सूखने के बाद ही पानी दें, तापमान लगभग 10°C से ऊपर रखें और बढ़वार के समय हल्का खाद दें।"
    },
    "zh": {
      "common_name": "福斯特狄克亚",
      "description": "Dyckia fosteriana 是原产巴西的地生凤梨科植物，形成坚硬带刺的莲座。需要非常明亮到直射日照，并使用排水良好的多肉/仙人掌土。基质充分干后再浇水，温度尽量保持在约10°C以上，生长期可少量施肥。"
    },
    "ja": {
      "common_name": "ディッキア・フォステリアナ",
      "description": "Dyckia fosteriana はブラジル原産の地生ブロメリアで、硬くトゲのあるロゼットを作ります。非常に明るい光〜日光と、水はけの良い多肉・サボテン用土が適します。用土がよく乾いてから水やりし、約10°C以上を保ち、生育期は控えめに施肥します。"
    },
    "ko": {
      "common_name": "포스터 디키아",
      "description": "Dyckia fosteriana는 브라질 원산의 지생 브로멜리아드로, 단단하고 가시가 있는 로제트를 이룹니다. 매우 밝은 빛~햇빛과 배수가 좋은 다육/선인장 흙이 필요합니다. 흙이 충분히 마른 뒤 물을 주고, 약 10°C 이상을 유지하며 생장기에는 약하게 비료를 줍니다."
    }
  },
  "sources": {
    "urls": [
      "https://powo.science.kew.org/taxon/urn:lsid:ipni.org:names:86252-2",
      "https://gardeningsolutions.ifas.ufl.edu/plants/ornamentals/dyckia/",
      "https://hort.extension.wisc.edu/articles/bromeliads/",
      "https://bromeliadsocietyhouston.org/common-genera/dyckia/",
      "https://gardenerspath.com/plants/houseplants/grow-dyckia/"
    ]
  }
}
