{
  "external_id": "lonicera_periclymenum",
  "name": "Honeysuckle",
  "latin": "Lonicera periclymenum",
  "sun": "medium",
  "water": "medium",
  "difficulty": "medium",
  "popular": false,
  "recommended_pot_materials": [
    "plastic",
    "ceramic"
  ],
  "recommended_soil_mixes": [
    "all-purpose",
    "green-plants"
  ],
  "water_required": true,
  "water_interval_days": 7,
  "moisture_required": false,
  "moisture_interval_days": null,
  "fertilize_required": true,
  "fertilize_interval_days": 30,
  "repot_required": true,
  "repot_interval_months": 24,
  "image_hero": "lonicera_periclymenum.jpg",
  "image_thumb": "lonicera_periclymenum.jpg",
  "traits": [
    {
      "key": "sun",
      "value": {
        "text": {
          "en": "Medium light",
          "pl": "Średnie światło",
          "de": "Mittleres Licht",
          "fr": "Lumière moyenne",
          "it": "Luce media",
          "es": "Luz media",
          "pt": "Luz média",
          "ar": "ضوء متوسط",
          "hi": "मध्यम रोशनी",
          "zh": "中等光照",
          "ja": "中程度の光",
          "ko": "중간 조명"
        }
      }
    },
    {
      "key": "soil",
      "value": {
        "text": {
          "en": "Well-drained soil",
          "pl": "Dobrze przepuszczalna gleba",
          "de": "Gut durchlässiger Boden",
          "fr": "Sol bien drainé",
          "it": "Terreno ben drenato",
          "es": "Suelo bien drenado",
          "pt": "Solo bem drenado",
          "ar": "تربة جيدة التصريف",
          "hi": "अच्छी तरह से जल निकासी वाली मिट्टी",
          "zh": "良好排水的土壤",
          "ja": "排水の良い土壌",
          "ko": "배수 좋은 토양"
        }
      }
    },
    {
      "key": "watering",
      "value": {
        "text": {
          "en": "Moderate watering",
          "pl": "Umiarkowane podlewanie",
          "de": "Mäßiges Gießen",
          "fr": "Arrosage modéré",
          "it": "Annaffiatura moderata",
          "es": "Riego moderado",
          "pt": "Rega moderada",
          "ar": "ري مبتدل",
          "hi": "मध्यम पानी देना",
          "zh": "适度浇水",
          "ja": "適度な水やり",
          "ko": "적당한 급수"
        }
      }
    },
    {
      "key": "difficulty",
      "value": {
        "text": {
          "en": "Medium",
          "pl": "Średni",
          "de": "Mittel",
          "fr": "Moyenne",
          "it": "Medio",
          "es": "Medio",
          "pt": "Médio",
          "ar": "متوسط",
          "hi": "मध्यम",
          "zh": "中等",
          "ja": "中級",
          "ko": "중간"
        }
      }
    },
    {
      "key": "temperature",
      "value": {
        "text": {
          "en": "15-25°C",
          "pl": "15-25°C",
          "de": "15-25°C",
          "fr": "15-25°C",
          "it": "15-25°C",
          "es": "15-25°C",
          "pt": "15-25°C",
          "ar": "15-25°C",
          "hi": "15-25°C",
          "zh": "15-25°C",
          "ja": "15-25°C",
          "ko": "15-25°C"
        }
      }
    },
    {
      "key": "humidity",
      "value": {
        "text": {
          "en": "Moderate humidity",
          "pl": "Umiarkowana wilgotność",
          "de": "Mäßige Luftfeuchtigkeit",
          "fr": "Humidité modérée",
          "it": "Umidità moderata",
          "es": "Humedad moderada",
          "pt": "Umidade moderada",
          "ar": "رطوبة معتدلة",
          "hi": "मध्यम आर्द्रता",
          "zh": "适度湿度",
          "ja": "適度な湿度",
          "ko": "적당한 습도"
        }
      }
    },
    {
      "key": "toxic",
      "value": {
        "text": {
          "en": "Toxic to pets",
          "pl": "Toksyczny dla zwierząt",
          "de": "Toxisch für Haustiere",
          "fr": "Toxique pour les animaux",
          "it": "Tossico per gli animali",
          "es": "Tóxico para mascotas",
          "pt": "Tóxico para animais",
          "ar": "سام للحيوانات الأليفة",
          "hi": "पालतू जानवरों के लिए विषाक्त",
          "zh": "对宠物有毒",
          "ja": "ペットに有毒",
          "ko": "애완동물에게 독성"
        }
      }
    },
    {
      "key": "growth",
      "value": {
        "text": {
          "en": "Fast growing",
          "pl": "Szybko rosnący",
          "de": "Schnell wachsend",
          "fr": "Croissance rapide",
          "it": "Crescita veloce",
          "es": "Crecimiento rápido",
          "pt": "Crescimento rápido",
          "ar": "نمو سريع",
          "hi": "तेजी से बढ़ने वाला",
          "zh": "快速生长",
          "ja": "成長が早い",
          "ko": "빠르게 성장"
        }
      }
    },
    {
      "key": "problems",
      "value": {
        "text": {
          "en": "Avoid overwatering",
          "pl": "Unikaj przelania",
          "de": "Vermeiden Sie Überwässerung",
          "fr": "Évitez l'excès d'eau",
          "it": "Evitare l'eccesso di acqua",
          "es": "Evitar el exceso de riego",
          "pt": "Evitar rega excessiva",
          "ar": "تجنب الري الزائد",
          "hi": "अفرा पानी से बचें",
          "zh": "避免过度浇水",
          "ja": "水のやりすぎに注意",
          "ko": "과도한 급수를 피하십시오"
        }
      }
    },
    {
      "key": "pests",
      "value": {
        "text": {
          "en": "Occasional pests",
          "pl": "Okazjonalne szkodniki",
          "de": "Gelegentliche Schädlinge",
          "fr": "Pestes occasionnelles",
          "it": "Pestiferi occasionali",
          "es": "Plagas ocasionales",
          "pt": "Pragas ocasionais",
          "ar": "آفات عرضية",
          "hi": "कभी-कभी कीट",
          "zh": "偶尔有害虫",
          "ja": "時々害虫",
          "ko": "가끔 해충"
        }
      }
    }
  ],
  "translations": {
    "en": {
      "common_name": "Honeysuckle",
      "description": "Lonicera periclymenum, commonly known as honeysuckle, is a fast-growing, climbing shrub with fragrant flowers. It thrives in moderate light and prefers well-drained soil."
    },
    "pl": {
      "common_name": "Wiciokrzew",
      "description": "Lonicera periclymenum, znany jako wiciokrzew, to szybko rosnący, pnący się krzew o pachnących kwiatach. Woli średnie światło i dobrze przepuszczalną glebę."
    },
    "de": {
      "common_name": "Geißblatt",
      "description": "Lonicera periclymenum, auch Geißblatt genannt, ist ein schnell wachsender, kletternder Strauch mit duftenden Blüten. Es bevorzugt mittleres Licht und gut durchlässigen Boden."
    },
    "fr": {
      "common_name": "Chèvrefeuille",
      "description": "Lonicera periclymenum, appelé chèvrefeuille, est un arbuste grimpant à croissance rapide et aux fleurs parfumées. Il préfère une lumière modérée et un sol bien drainé."
    },
    "it": {
      "common_name": "Caprifoglio",
      "description": "Lonicera periclymenum, noto come caprifoglio, è un arbusto rampicante a crescita rapida con fiori profumati. Predilige luce media e terreno ben drenato."
    },
    "es": {
      "common_name": "Madreselva",
      "description": "Lonicera periclymenum, conocida como madreselva, es un arbusto trepador de rápido crecimiento con flores fragantes. Prefiere luz moderada y suelo bien drenado."
    },
    "pt": {
      "common_name": "Madressilva",
      "description": "Lonicera periclymenum, conhecida como madressilva, é um arbusto trepador de crescimento rápido com flores perfumadas. Prefere luz moderada e solo bem drenado."
    },
    "ar": {
      "common_name": "شجرة العسل",
      "description": "Lonicera periclymenum، والمعروفة بشجرة العسل، هي شجيرة متسلقة سريعة النمو ذات زهور عطرة. يفضل الضوء المعتدل والتربة جيدة التصريف."
    },
    "hi": {
      "common_name": "हनीसकल",
      "description": "Lonicera periclymenum, जिसे हनीसकल के नाम से जाना जाता है, एक तेजी से बढ़ने वाली बेलदार झाड़ी है जिसमें खुशबूदार फूल होते हैं। यह मध्यम रोशनी में बढ़ता है और अच्छी तरह से जल निकासी वाली मिट्टी पसंद करता है।"
    },
    "zh": {
      "common_name": "忍冬",
      "description": "Lonicera periclymenum，通常称为忍冬，是一种快速生长的攀缘灌木，开着芬芳的花朵。它喜欢中等光照和排水良好的土壤。"
    },
    "ja": {
      "common_name": "スイカズラ",
      "description": "Lonicera periclymenum、通称スイカズラは、芳香のある花を咲かせる速く成長するつる性の低木です。中程度の光と排水の良い土壌を好みます。"
    },
    "ko": {
      "common_name": "인동초",
      "description": "Lonicera periclymenum, 일반적으로 인동초로 알려진 이 식물은 빠르게 자라는 덩굴식물로 향기로운 꽃을 가지고 있습니다. 중간 정도의 빛과 배수가 좋은 토양을 선호합니다."
    }
  },
  "sources": {
    "urls": [
      "https://www.rhs.org.uk/plants/lonicera-periclymenum",
      "https://www.bhg.com/gardening/pests-insects-diseases/growing-honeysuckle/"
    ]
  }
}
