{
  "external_id": "saintpaulia_ionantha",
  "name": "African Violet",
  "latin": "Saintpaulia ionantha",
  "sun": "medium",
  "water": "medium",
  "difficulty": "easy",
  "popular": false,
  "recommended_pot_materials": [
    "plastic",
    "ceramic"
  ],
  "recommended_soil_mixes": [
    "universal",
    "acidic"
  ],
  "water_required": true,
  "water_interval_days": 7,
  "moisture_required": false,
  "moisture_interval_days": null,
  "fertilize_required": true,
  "fertilize_interval_days": 30,
  "repot_required": true,
  "repot_interval_months": 12,
  "image_hero": "saintpaulia_ionantha.jpg",
  "image_thumb": "saintpaulia_ionantha.jpg",
  "traits": [
    {
      "key": "sun",
      "value": {
        "text": {
          "en": "medium",
          "pl": "średnie",
          "de": "mittel",
          "fr": "moyenne",
          "it": "media",
          "es": "media",
          "pt": "média",
          "ar": "متوسط",
          "hi": "मध्यम",
          "zh": "中等",
          "ja": "中程度",
          "ko": "중간"
        }
      }
    },
    {
      "key": "soil",
      "value": {
        "text": {
          "en": "universal",
          "pl": "uniwersalna",
          "de": "universell",
          "fr": "universel",
          "it": "universale",
          "es": "universal",
          "pt": "universal",
          "ar": "عالمي",
          "hi": "सार्वभौमिक",
          "zh": "通用",
          "ja": "ユニバーサル",
          "ko": "보편적인"
        }
      }
    },
    {
      "key": "watering",
      "value": {
        "text": {
          "en": "medium",
          "pl": "średnie",
          "de": "mittel",
          "fr": "moyenne",
          "it": "media",
          "es": "media",
          "pt": "média",
          "ar": "متوسط",
          "hi": "मध्यम",
          "zh": "中等",
          "ja": "中程度",
          "ko": "중간"
        }
      }
    },
    {
      "key": "difficulty",
      "value": {
        "text": {
          "en": "easy",
          "pl": "łatwe",
          "de": "einfach",
          "fr": "facile",
          "it": "facile",
          "es": "fácil",
          "pt": "fácil",
          "ar": "سهل",
          "hi": "आसान",
          "zh": "简单",
          "ja": "簡単",
          "ko": "쉬운"
        }
      }
    },
    {
      "key": "temperature",
      "value": {
        "text": {
          "en": "20-24°C",
          "pl": "20-24°C",
          "de": "20-24°C",
          "fr": "20-24°C",
          "it": "20-24°C",
          "es": "20-24°C",
          "pt": "20-24°C",
          "ar": "20-24°C",
          "hi": "20-24°C",
          "zh": "20-24°C",
          "ja": "20-24°C",
          "ko": "20-24°C"
        }
      }
    },
    {
      "key": "humidity",
      "value": {
        "text": {
          "en": "medium",
          "pl": "średnia",
          "de": "mittel",
          "fr": "moyenne",
          "it": "media",
          "es": "media",
          "pt": "média",
          "ar": "متوسط",
          "hi": "मध्यम",
          "zh": "中等",
          "ja": "中程度",
          "ko": "중간"
        }
      }
    },
    {
      "key": "toxic",
      "value": {
        "text": {
          "en": "no",
          "pl": "nie",
          "de": "nein",
          "fr": "non",
          "it": "no",
          "es": "no",
          "pt": "não",
          "ar": "لا",
          "hi": "नहीं",
          "zh": "否",
          "ja": "いいえ",
          "ko": "아니오"
        }
      }
    },
    {
      "key": "growth",
      "value": {
        "text": {
          "en": "slow",
          "pl": "wolny",
          "de": "langsam",
          "fr": "lent",
          "it": "lento",
          "es": "lento",
          "pt": "lento",
          "ar": "بطيء",
          "hi": "धीमा",
          "zh": "慢",
          "ja": "遅い",
          "ko": "느림"
        }
      }
    }
  ],
  "translations": {
    "en": {
      "common_name": "African Violet",
      "description": "Saintpaulia ionantha, commonly known as African Violet, is a popular indoor plant appreciated for its beautiful purple flowers. It thrives in indirect sunlight and moderate watering."
    },
    "pl": {
      "common_name": "fiołek afrykański",
      "description": "Saintpaulia ionantha, znany jako fiołek afrykański, jest popularną rośliną doniczkową cenioną za piękne fioletowe kwiaty. Rośnie najlepiej w pośrednim świetle i umiarkowanym podlewaniu."
    },
    "de": {
      "common_name": "Afrikanisches Veilchen",
      "description": "Saintpaulia ionantha, auch als Afrikanisches Veilchen bekannt, ist eine beliebte Zimmerpflanze, die für ihre schönen violetten Blumen geschätzt wird. Sie gedeiht bei indirekter Sonneneinstrahlung und mäßigem Gießen."
    },
    "fr": {
      "common_name": "Violette africaine",
      "description": "Saintpaulia ionantha, connue sous le nom de violette africaine, est une plante d'intérieur populaire appréciée pour ses belles fleurs violettes. Elle prospère sous une lumière indirecte et avec un arrosage modéré."
    },
    "it": {
      "common_name": "Violetta africana",
      "description": "Saintpaulia ionantha, conosciuta come violetta africana, è una pianta da interno molto apprezzata per i suoi bellissimi fiori viola. Cresce meglio con luce indiretta e irrigazione moderata."
    },
    "es": {
      "common_name": "Violeta africana",
      "description": "Saintpaulia ionantha, conocida como violeta africana, es una planta de interior popular apreciada por sus hermosas flores moradas. Crece mejor con luz indirecta y riego moderado."
    },
    "pt": {
      "common_name": "Violeta africana",
      "description": "Saintpaulia ionantha, conhecida como violeta africana, é uma planta de interior popular apreciada por suas belas flores roxas. Ela cresce melhor com luz indireta e rega moderada."
    },
    "ar": {
      "common_name": "أفريقي البنفسج",
      "description": "سانتبوليا إيونانثا، والمعروفة باسم البنفسج الأفريقي، هي نبات منزلي شهير يتميز بأزهارها البنفسجية الجميلة. ينمو بشكل أفضل في الضوء غير المباشر والري المعتدل."
    },
    "hi": {
      "common_name": "अफ्रीकी वायलेट",
      "description": "सैंटपूलिया आयोनांथा, जिसे अफ्रीकी वायलेट के नाम से जाना जाता है, एक लोकप्रिय इनडोर पौधा है जिसे इसके सुंदर बैंगनी फूलों के लिए सराहा जाता है। यह अप्रत्यक्ष सूर्यप्रकाश और मध्यम जलने में अच्छा करता है।"
    },
    "zh": {
      "common_name": "非洲紫罗兰",
      "description": "圣保利亚·艾昂安莎，通常称为非洲紫罗兰，是一种受欢迎的室内植物，因其美丽的紫色花朵而受到喜爱。它在间接阳光和适度浇水下茁壮成长。"
    },
    "ja": {
      "common_name": "アフリカスミレ",
      "description": "サイントパウリア・イオナンサ、アフリカスミレとして知られるこの植物は、美しい紫色の花で人気があります。間接的な日光と適度な水やりでよく育ちます。"
    },
    "ko": {
      "common_name": "아프리카 제비꽃",
      "description": "세인트폴리아 이오난타, 일반적으로 아프리카 제비꽃으로 알려진 이 식물은 아름다운 보라색 꽃으로 인기가 있습니다. 간접적인 햇빛과 적당한 물주기로 잘 자랍니다."
    }
  },
  "sources": {
    "urls": [
      "https://www.botanicalgardens.com/africanviolet",
      "https://www.gardeners.com/plant-care/african-violet"
    ]
  }
}
